LICENSE.rst
README.md
setup.cfg
setup.py
ravpy/__init__.py
ravpy/config.py
ravpy/globals.py
ravpy/initialize.py
ravpy/logger.py
ravpy/singleton_utils.py
ravpy/strings.py
ravpy/utils.py
ravpy.egg-info/PKG-INFO
ravpy.egg-info/SOURCES.txt
ravpy.egg-info/dependency_links.txt
ravpy.egg-info/requires.txt
ravpy.egg-info/top_level.txt
ravpy/db/__init__.py
ravpy/db/manager.py
ravpy/db/models.py
ravpy/distributed/__init__.py
ravpy/distributed/benchmarking.py
ravpy/distributed/compute.py
ravpy/distributed/evaluate.py
ravpy/distributed/participate.py
ravpy/distributed/op_functions/__init__.py
ravpy/distributed/op_functions/dl_ops.py
ravpy/distributed/op_functions/math_ops.py
ravpy/distributed/op_functions/ml_ops.py
ravpy/distributed/op_functions/utils.py
ravpy/federated/__init__.py
ravpy/federated/compute.py
ravpy/federated/participate.py
ravpy/ftp/__init__.py
ravpy/socket/__init__.py
ravpy/socket/socket_client.py