Metadata-Version: 2.1
Name: ravpy
Version: 0.20
Summary: UNKNOWN
Home-page: https://github.com/ravenprotocol/ravpy
Author: Raven Protocol
Author-email: kailash@ravenprotocol.com
License: MIT
Keywords: Ravpy,python client library for providers
Platform: UNKNOWN
License-File: LICENSE.rst
